curry_fp/__init__.py
curry_fp/curry.py
curry_fp-1.3.3.dist-info/LICENSE
curry_fp-1.3.3.dist-info/METADATA
curry_fp-1.3.3.dist-info/WHEEL
curry_fp-1.3.3.dist-info/RECORD
